README.txt
setup.py
docs/HISTORY.txt
docs/INSTALL.txt
docs/LICENSE.GPL
docs/LICENSE.txt
webcouturier/__init__.py
webcouturier.icompany.theme.egg-info/PKG-INFO
webcouturier.icompany.theme.egg-info/SOURCES.txt
webcouturier.icompany.theme.egg-info/dependency_links.txt
webcouturier.icompany.theme.egg-info/entry_points.txt
webcouturier.icompany.theme.egg-info/namespace_packages.txt
webcouturier.icompany.theme.egg-info/not-zip-safe
webcouturier.icompany.theme.egg-info/requires.txt
webcouturier.icompany.theme.egg-info/top_level.txt
webcouturier/icompany/__init__.py
webcouturier/icompany/theme/__init__.py
webcouturier/icompany/theme/configure.zcml
webcouturier/icompany/theme/profiles.zcml
webcouturier/icompany/theme/setuphandlers.py
webcouturier/icompany/theme/skins.zcml
webcouturier/icompany/theme/tests.py
webcouturier/icompany/theme/version.txt
webcouturier/icompany/theme/browser/__init__.py
webcouturier/icompany/theme/browser/configure.zcml
webcouturier/icompany/theme/browser/interfaces.py
webcouturier/icompany/theme/browser/viewlets.py
webcouturier/icompany/theme/browser/templates/footer.pt
webcouturier/icompany/theme/browser/templates/webcouturier_searchbox.pt
webcouturier/icompany/theme/browser/templates/webcouturier_sections.pt
webcouturier/icompany/theme/browser/templates/webcouturier_subsections.pt
webcouturier/icompany/theme/portlets/__init__.py
webcouturier/icompany/theme/portlets/configure.zcml
webcouturier/icompany/theme/portlets/webcouturier_login.pt
webcouturier/icompany/theme/profiles/default/cssregistry.xml
webcouturier/icompany/theme/profiles/default/import_steps.xml
webcouturier/icompany/theme/profiles/default/skins.xml
webcouturier/icompany/theme/profiles/default/viewlets.xml
webcouturier/icompany/theme/profiles/default/webcouturier.icompany.theme_various.txt
webcouturier/icompany/theme/skins/webcouturier_icompany_theme_custom_images/CONTENT.txt
webcouturier/icompany/theme/skins/webcouturier_icompany_theme_custom_images/below_tabs_left.png
webcouturier/icompany/theme/skins/webcouturier_icompany_theme_custom_images/below_tabs_right.png
webcouturier/icompany/theme/skins/webcouturier_icompany_theme_custom_images/bullet.gif
webcouturier/icompany/theme/skins/webcouturier_icompany_theme_custom_images/bullet.gif.metadata
webcouturier/icompany/theme/skins/webcouturier_icompany_theme_custom_images/bullet_black_bg.png
