Metadata-Version: 1.0
Name: webcouturier.icompany.theme
Version: 1.0
Summary: Plone theme in blue/green colors
Home-page: http://www.webcouturier.com
Author: Denys Mishunov
Author-email: denis@webcouturier.c.com
License: GPL
Keywords: web couturier plone zope theme
Platform: UNKNOWN
Classifier: Framework :: Plone
Classifier: Framework :: Zope2
Classifier: Framework :: Zope3
Classifier: Programming Language :: Python
Classifier: Topic :: Software Development :: Libraries :: Python Modules
